ndex/__init__.py
ndex/ndpull/__init__.py
ndex/ndpull/boss_resources.py
ndex/ndpull/ndpull.py
ndex/ndpush/__init__.py
ndex/ndpush/boss_resources.py
ndex/ndpush/ingest_job.py
ndex/ndpush/ingest_large_vol.py
ndex/ndpush/parse_log.py
ndex/ndpush/render_resource.py
ndex/ndpush/repeat_cutouts.py
scripts/__init__.py
scripts/expand_stacks.py
scripts/ingest_catmaid.py
ndexchange-1.0.10.dist-info/LICENSE
ndexchange-1.0.10.dist-info/METADATA
ndexchange-1.0.10.dist-info/WHEEL
ndexchange-1.0.10.dist-info/entry_points.txt
ndexchange-1.0.10.dist-info/top_level.txt
ndexchange-1.0.10.dist-info/RECORD
