Metadata-Version: 2.1
Name: ndexchange
Version: 1.0.10
Summary: Python 3 program to download data from NeuroData
Home-page: https://github.com/neurodata/ndex
Author: Benjamin Falk
Author-email: falk.ben@jhu.edu
License: Apache 2.0
Keywords: brain,microscopy,neuroscience,connectome,connectomics,spatial,EM,electron,calcium,database,boss
Platform: UNKNOWN
Requires-Python: >=3.5
Requires-Dist: blosc (==1.4.4)
Requires-Dist: requests (==2.21.0)
Requires-Dist: numpy (==1.15.2)
Requires-Dist: tifffile (==0.15.1)
Requires-Dist: Pillow (==5.3.0)
Requires-Dist: tqdm (==4.26.0)
Requires-Dist: intern (==0.9.10)
Requires-Dist: slacker (==0.9.65)
Requires-Dist: boto3 (==1.9.17)
Requires-Dist: tailer (==0.4.1)
Requires-Dist: pypng (==0.0.18)
Requires-Dist: nibabel (==2.3.0)
